{
    "id":5,
    "length":20,
    "level":{
        "objects": {
                "bush":[
                ],
                "sky":[
                ],
                "cloud":[
                ],
                "pipe":[
                ],
                "ground":[

                ]
            },
        "layers": {
                "sky":{
                    "x":[0,40],
                    "y":[0,13]
                },
                "ground":{
                    "x":[0,40],
                    "y":[14,16]
                }
            },
        "entities": {
                "CoinBox":[
                ],
                "coinBrick":[
                    
                ],
                "coin":[
                    

                ],
                "Goomba":[
                ],
                "Koopa":[
                ],
                "RandomBox":[
                ]
        },
        "Mario":{
            "position":[1,5]
        }

    }
}